{
	"kind" : "toolchains",
	"toolchains" : 
	[
		{
			"compiler" : 
			{
				"id" : "GNU",
				"implicit" : 
				{
					"includeDirectories" : 
					[
						"C:/IT/MinGW/lib/gcc/mingw32/6.3.0/include",
						"C:/IT/MinGW/include",
						"C:/IT/MinGW/lib/gcc/mingw32/6.3.0/include-fixed",
						"C:/IT/MinGW/mingw32/include"
					],
					"linkDirectories" : 
					[
						"C:/IT/MinGW/lib/gcc/mingw32/6.3.0",
						"C:/IT/MinGW/lib/gcc",
						"C:/IT/MinGW/mingw32/lib",
						"C:/IT/MinGW/lib"
					],
					"linkFrameworkDirectories" : [],
					"linkLibraries" : 
					[
						"mingw32",
						"gcc",
						"moldname",
						"mingwex",
						"advapi32",
						"shell32",
						"user32",
						"kernel32",
						"mingw32",
						"gcc",
						"moldname",
						"mingwex"
					]
				},
				"path" : "C:/IT/MinGW/bin/gcc.exe",
				"version" : "6.3.0"
			},
			"language" : "C",
			"sourceFileExtensions" : 
			[
				"c",
				"m"
			]
		},
		{
			"compiler" : 
			{
				"id" : "GNU",
				"implicit" : 
				{
					"includeDirectories" : 
					[
						"C:/IT/MinGW/lib/gcc/mingw32/6.3.0/include/c++",
						"C:/IT/MinGW/lib/gcc/mingw32/6.3.0/include/c++/mingw32",
						"C:/IT/MinGW/lib/gcc/mingw32/6.3.0/include/c++/backward",
						"C:/IT/MinGW/lib/gcc/mingw32/6.3.0/include",
						"C:/IT/MinGW/include",
						"C:/IT/MinGW/lib/gcc/mingw32/6.3.0/include-fixed",
						"C:/IT/MinGW/mingw32/include"
					],
					"linkDirectories" : 
					[
						"C:/IT/MinGW/lib/gcc/mingw32/6.3.0",
						"C:/IT/MinGW/lib/gcc",
						"C:/IT/MinGW/mingw32/lib",
						"C:/IT/MinGW/lib"
					],
					"linkFrameworkDirectories" : [],
					"linkLibraries" : 
					[
						"stdc++",
						"mingw32",
						"gcc_s",
						"gcc",
						"moldname",
						"mingwex",
						"advapi32",
						"shell32",
						"user32",
						"kernel32",
						"mingw32",
						"gcc_s",
						"gcc",
						"moldname",
						"mingwex"
					]
				},
				"path" : "C:/IT/MinGW/bin/g++.exe",
				"version" : "6.3.0"
			},
			"language" : "CXX",
			"sourceFileExtensions" : 
			[
				"C",
				"M",
				"c++",
				"cc",
				"cpp",
				"cxx",
				"mm",
				"mpp",
				"CPP",
				"ixx",
				"cppm",
				"ccm",
				"cxxm",
				"c++m"
			]
		},
		{
			"compiler" : 
			{
				"implicit" : {},
				"path" : "C:/IT/MinGW/bin/windres.exe"
			},
			"language" : "RC",
			"sourceFileExtensions" : 
			[
				"rc",
				"RC"
			]
		}
	],
	"version" : 
	{
		"major" : 1,
		"minor" : 0
	}
}
